loginid/__init__.py
loginid/loginid.py
loginid/management.py
loginid/core/__init__.py
loginid/core/auth.py
loginid/core/client.py
loginid/core/cred.py
loginid/core/errors.py
loginid/managements/__init__.py
loginid/managements/code_mgmt.py
loginid/managements/cred_mgmt.py
loginid/managements/user_mgmt.py
loginid-0.1.5.dist-info/METADATA
loginid-0.1.5.dist-info/WHEEL
loginid-0.1.5.dist-info/top_level.txt
loginid-0.1.5.dist-info/RECORD
