Metadata-Version: 2.1
Name: loginid
Version: 0.1.5
Summary: Interface SDK for LoginID infrastructure
Home-page: https://loginid.io
Author: Quang Hoang
Author-email: quang@loginid.io
License: UNKNOWN
Project-URL: Documentation, https://docs.loginid.io/Server-SDKs/Python/python-get-started
Platform: UNKNOWN
Classifier: Programming Language :: Python :: 3
Classifier: License :: OSI Approved :: MIT License
Classifier: Operating System :: OS Independent
Requires-Python: >=3.6
Requires-Dist: requests
Requires-Dist: cryptography
Requires-Dist: pyjwt
